repository2prompt/__init__.py
repository2prompt/cli.py
repository2prompt/config.py
repository2prompt/default_config.yaml
repository2prompt/repository2prompt.py
repository2prompt/templates/default_template.j2
repository2prompt/templates/detailed_template.j2
repository2prompt/utils/__init__.py
repository2prompt/utils/common.py
repository2prompt/utils/file_processor.py
repository2prompt/utils/github_api.py
repository2prompt/utils/input_handler.py
repository2prompt/utils/output_formatter.py
repository2prompt/utils/template_renderer.py
repository2prompt-1.0.0.dist-info/LICENSE
repository2prompt-1.0.0.dist-info/METADATA
repository2prompt-1.0.0.dist-info/WHEEL
repository2prompt-1.0.0.dist-info/entry_points.txt
repository2prompt-1.0.0.dist-info/top_level.txt
repository2prompt-1.0.0.dist-info/RECORD
