Metadata-Version: 2.2
Name: repository2prompt
Version: 1.0.0
Summary: A tool to convert GitHub repositories into LLM prompts
Home-page: https://github.com/wctsai20002/repository2prompt
Author: tweichuan
Author-email: wctsai20002@gmail.com
Classifier: Programming Language :: Python :: 3
Classifier: License :: OSI Approved :: MIT License
Classifier: Operating System :: OS Independent
Requires-Python: >=3.7
License-File: LICENSE
Requires-Dist: pyyaml>=6.0
Requires-Dist: requests>=2.26.0
Requires-Dist: jinja2>=3.0.1
Dynamic: author
Dynamic: author-email
Dynamic: classifier
Dynamic: description
Dynamic: description-content-type
Dynamic: home-page
Dynamic: requires-dist
Dynamic: requires-python
Dynamic: summary
